timefunc/__init__.py
timefunc/timer.py
pytimefunc_rj-1.0.0.dist-info/METADATA
pytimefunc_rj-1.0.0.dist-info/WHEEL
pytimefunc_rj-1.0.0.dist-info/RECORD
